{"nodes": [{"id": "d_ai_jim_docs_archive_live_daemon_testing_log_md", "label": "LIVE_DAEMON_TESTING_LOG.md", "file_type": "document", "source_file": "D:\\AI\\Jim\\docs_archive\\LIVE_DAEMON_TESTING_LOG.md", "source_location": "L1"}, {"id": "docs_archive_live_daemon_testing_log_live_daemon_testing_log_phase_2_parallel", "label": "\ud83d\udcca LIVE DAEMON TESTING LOG (Phase 2 Parallel)", "file_type": "document", "source_file": "D:\\AI\\Jim\\docs_archive\\LIVE_DAEMON_TESTING_LOG.md", "source_location": "L1"}, {"id": "docs_archive_live_daemon_testing_log_testing_overview", "label": "\ud83d\udccb Testing Overview", "file_type": "document", "source_file": "D:\\AI\\Jim\\docs_archive\\LIVE_DAEMON_TESTING_LOG.md", "source_location": "L8"}, {"id": "docs_archive_live_daemon_testing_log_scheduler_configuration", "label": "\ud83d\udd50 Scheduler Configuration", "file_type": "document", "source_file": "D:\\AI\\Jim\\docs_archive\\LIVE_DAEMON_TESTING_LOG.md", "source_location": "L24"}, {"id": "docs_archive_live_daemon_testing_log_codeblock_1", "label": "code:powershell (# Run daily at 08:00 UTC)", "file_type": "document", "source_file": "D:\\AI\\Jim\\docs_archive\\LIVE_DAEMON_TESTING_LOG.md", "source_location": "L34"}, {"id": "docs_archive_live_daemon_testing_log_daily_records", "label": "\ud83d\udcc5 Daily Records", "file_type": "document", "source_file": "D:\\AI\\Jim\\docs_archive\\LIVE_DAEMON_TESTING_LOG.md", "source_location": "L42"}, {"id": "docs_archive_live_daemon_testing_log_day_1_may_13_2026", "label": "**Day 1: May 13, 2026**", "file_type": "document", "source_file": "D:\\AI\\Jim\\docs_archive\\LIVE_DAEMON_TESTING_LOG.md", "source_location": "L44"}, {"id": "docs_archive_live_daemon_testing_log_day_2_may_14_2026", "label": "**Day 2: May 14, 2026**", "file_type": "document", "source_file": "D:\\AI\\Jim\\docs_archive\\LIVE_DAEMON_TESTING_LOG.md", "source_location": "L73"}, {"id": "docs_archive_live_daemon_testing_log_day_3_may_15_2026", "label": "**Day 3: May 15, 2026**", "file_type": "document", "source_file": "D:\\AI\\Jim\\docs_archive\\LIVE_DAEMON_TESTING_LOG.md", "source_location": "L88"}, {"id": "docs_archive_live_daemon_testing_log_day_4_may_16_2026", "label": "**Day 4: May 16, 2026**", "file_type": "document", "source_file": "D:\\AI\\Jim\\docs_archive\\LIVE_DAEMON_TESTING_LOG.md", "source_location": "L100"}, {"id": "docs_archive_live_daemon_testing_log_day_5_may_17_2026", "label": "**Day 5: May 17, 2026**", "file_type": "document", "source_file": "D:\\AI\\Jim\\docs_archive\\LIVE_DAEMON_TESTING_LOG.md", "source_location": "L112"}, {"id": "docs_archive_live_daemon_testing_log_day_6_may_18_2026", "label": "**Day 6: May 18, 2026**", "file_type": "document", "source_file": "D:\\AI\\Jim\\docs_archive\\LIVE_DAEMON_TESTING_LOG.md", "source_location": "L124"}, {"id": "docs_archive_live_daemon_testing_log_day_7_may_19_2026", "label": "**Day 7: May 19, 2026**", "file_type": "document", "source_file": "D:\\AI\\Jim\\docs_archive\\LIVE_DAEMON_TESTING_LOG.md", "source_location": "L136"}, {"id": "docs_archive_live_daemon_testing_log_performance_baseline_to_fill_during_testing", "label": "\ud83d\udcca Performance Baseline (To Fill During Testing)", "file_type": "document", "source_file": "D:\\AI\\Jim\\docs_archive\\LIVE_DAEMON_TESTING_LOG.md", "source_location": "L150"}, {"id": "docs_archive_live_daemon_testing_log_expected_metrics_from_initial_test", "label": "Expected Metrics (from initial test)", "file_type": "document", "source_file": "D:\\AI\\Jim\\docs_archive\\LIVE_DAEMON_TESTING_LOG.md", "source_location": "L152"}, {"id": "docs_archive_live_daemon_testing_log_observed_baseline_will_fill", "label": "Observed Baseline (Will Fill)", "file_type": "document", "source_file": "D:\\AI\\Jim\\docs_archive\\LIVE_DAEMON_TESTING_LOG.md", "source_location": "L160"}, {"id": "docs_archive_live_daemon_testing_log_issues_resolutions", "label": "\ud83d\udea8 Issues & Resolutions", "file_type": "document", "source_file": "D:\\AI\\Jim\\docs_archive\\LIVE_DAEMON_TESTING_LOG.md", "source_location": "L169"}, {"id": "docs_archive_live_daemon_testing_log_issue_tracking", "label": "Issue Tracking", "file_type": "document", "source_file": "D:\\AI\\Jim\\docs_archive\\LIVE_DAEMON_TESTING_LOG.md", "source_location": "L171"}, {"id": "docs_archive_live_daemon_testing_log_parallel_tasks", "label": "\u2705 Parallel Tasks", "file_type": "document", "source_file": "D:\\AI\\Jim\\docs_archive\\LIVE_DAEMON_TESTING_LOG.md", "source_location": "L180"}, {"id": "docs_archive_live_daemon_testing_log_daily_checklist", "label": "\ud83d\udccb Daily Checklist", "file_type": "document", "source_file": "D:\\AI\\Jim\\docs_archive\\LIVE_DAEMON_TESTING_LOG.md", "source_location": "L196"}, {"id": "docs_archive_live_daemon_testing_log_success_criteria_tracker", "label": "\ud83c\udfaf Success Criteria Tracker", "file_type": "document", "source_file": "D:\\AI\\Jim\\docs_archive\\LIVE_DAEMON_TESTING_LOG.md", "source_location": "L214"}, {"id": "docs_archive_live_daemon_testing_log_end_of_test_summary_to_complete_may_20", "label": "\ud83d\udcc8 End-of-Test Summary (To Complete May 20)", "file_type": "document", "source_file": "D:\\AI\\Jim\\docs_archive\\LIVE_DAEMON_TESTING_LOG.md", "source_location": "L226"}, {"id": "docs_archive_live_daemon_testing_log_phase_2_completion", "label": "\ud83c\udf81 Phase 2 Completion", "file_type": "document", "source_file": "D:\\AI\\Jim\\docs_archive\\LIVE_DAEMON_TESTING_LOG.md", "source_location": "L242"}], "edges": [{"source": "d_ai_jim_docs_archive_live_daemon_testing_log_md", "target": "docs_archive_live_daemon_testing_log_live_daemon_testing_log_phase_2_parallel", "relation": "contains", "confidence": "EXTRACTED", "source_file": "D:\\AI\\Jim\\docs_archive\\LIVE_DAEMON_TESTING_LOG.md", "source_location": "L1", "weight": 1.0}, {"source": "docs_archive_live_daemon_testing_log_live_daemon_testing_log_phase_2_parallel", "target": "docs_archive_live_daemon_testing_log_testing_overview", "relation": "contains", "confidence": "EXTRACTED", "source_file": "D:\\AI\\Jim\\docs_archive\\LIVE_DAEMON_TESTING_LOG.md", "source_location": "L8", "weight": 1.0}, {"source": "docs_archive_live_daemon_testing_log_live_daemon_testing_log_phase_2_parallel", "target": "docs_archive_live_daemon_testing_log_scheduler_configuration", "relation": "contains", "confidence": "EXTRACTED", "source_file": "D:\\AI\\Jim\\docs_archive\\LIVE_DAEMON_TESTING_LOG.md", "source_location": "L24", "weight": 1.0}, {"source": "docs_archive_live_daemon_testing_log_scheduler_configuration", "target": "docs_archive_live_daemon_testing_log_codeblock_1", "relation": "contains", "confidence": "EXTRACTED", "source_file": "D:\\AI\\Jim\\docs_archive\\LIVE_DAEMON_TESTING_LOG.md", "source_location": "L34", "weight": 1.0}, {"source": "docs_archive_live_daemon_testing_log_live_daemon_testing_log_phase_2_parallel", "target": "docs_archive_live_daemon_testing_log_daily_records", "relation": "contains", "confidence": "EXTRACTED", "source_file": "D:\\AI\\Jim\\docs_archive\\LIVE_DAEMON_TESTING_LOG.md", "source_location": "L42", "weight": 1.0}, {"source": "docs_archive_live_daemon_testing_log_daily_records", "target": "docs_archive_live_daemon_testing_log_day_1_may_13_2026", "relation": "contains", "confidence": "EXTRACTED", "source_file": "D:\\AI\\Jim\\docs_archive\\LIVE_DAEMON_TESTING_LOG.md", "source_location": "L44", "weight": 1.0}, {"source": "docs_archive_live_daemon_testing_log_daily_records", "target": "docs_archive_live_daemon_testing_log_day_2_may_14_2026", "relation": "contains", "confidence": "EXTRACTED", "source_file": "D:\\AI\\Jim\\docs_archive\\LIVE_DAEMON_TESTING_LOG.md", "source_location": "L73", "weight": 1.0}, {"source": "docs_archive_live_daemon_testing_log_daily_records", "target": "docs_archive_live_daemon_testing_log_day_3_may_15_2026", "relation": "contains", "confidence": "EXTRACTED", "source_file": "D:\\AI\\Jim\\docs_archive\\LIVE_DAEMON_TESTING_LOG.md", "source_location": "L88", "weight": 1.0}, {"source": "docs_archive_live_daemon_testing_log_daily_records", "target": "docs_archive_live_daemon_testing_log_day_4_may_16_2026", "relation": "contains", "confidence": "EXTRACTED", "source_file": "D:\\AI\\Jim\\docs_archive\\LIVE_DAEMON_TESTING_LOG.md", "source_location": "L100", "weight": 1.0}, {"source": "docs_archive_live_daemon_testing_log_daily_records", "target": "docs_archive_live_daemon_testing_log_day_5_may_17_2026", "relation": "contains", "confidence": "EXTRACTED", "source_file": "D:\\AI\\Jim\\docs_archive\\LIVE_DAEMON_TESTING_LOG.md", "source_location": "L112", "weight": 1.0}, {"source": "docs_archive_live_daemon_testing_log_daily_records", "target": "docs_archive_live_daemon_testing_log_day_6_may_18_2026", "relation": "contains", "confidence": "EXTRACTED", "source_file": "D:\\AI\\Jim\\docs_archive\\LIVE_DAEMON_TESTING_LOG.md", "source_location": "L124", "weight": 1.0}, {"source": "docs_archive_live_daemon_testing_log_daily_records", "target": "docs_archive_live_daemon_testing_log_day_7_may_19_2026", "relation": "contains", "confidence": "EXTRACTED", "source_file": "D:\\AI\\Jim\\docs_archive\\LIVE_DAEMON_TESTING_LOG.md", "source_location": "L136", "weight": 1.0}, {"source": "docs_archive_live_daemon_testing_log_live_daemon_testing_log_phase_2_parallel", "target": "docs_archive_live_daemon_testing_log_performance_baseline_to_fill_during_testing", "relation": "contains", "confidence": "EXTRACTED", "source_file": "D:\\AI\\Jim\\docs_archive\\LIVE_DAEMON_TESTING_LOG.md", "source_location": "L150", "weight": 1.0}, {"source": "docs_archive_live_daemon_testing_log_performance_baseline_to_fill_during_testing", "target": "docs_archive_live_daemon_testing_log_expected_metrics_from_initial_test", "relation": "contains", "confidence": "EXTRACTED", "source_file": "D:\\AI\\Jim\\docs_archive\\LIVE_DAEMON_TESTING_LOG.md", "source_location": "L152", "weight": 1.0}, {"source": "docs_archive_live_daemon_testing_log_performance_baseline_to_fill_during_testing", "target": "docs_archive_live_daemon_testing_log_observed_baseline_will_fill", "relation": "contains", "confidence": "EXTRACTED", "source_file": "D:\\AI\\Jim\\docs_archive\\LIVE_DAEMON_TESTING_LOG.md", "source_location": "L160", "weight": 1.0}, {"source": "docs_archive_live_daemon_testing_log_live_daemon_testing_log_phase_2_parallel", "target": "docs_archive_live_daemon_testing_log_issues_resolutions", "relation": "contains", "confidence": "EXTRACTED", "source_file": "D:\\AI\\Jim\\docs_archive\\LIVE_DAEMON_TESTING_LOG.md", "source_location": "L169", "weight": 1.0}, {"source": "docs_archive_live_daemon_testing_log_issues_resolutions", "target": "docs_archive_live_daemon_testing_log_issue_tracking", "relation": "contains", "confidence": "EXTRACTED", "source_file": "D:\\AI\\Jim\\docs_archive\\LIVE_DAEMON_TESTING_LOG.md", "source_location": "L171", "weight": 1.0}, {"source": "docs_archive_live_daemon_testing_log_live_daemon_testing_log_phase_2_parallel", "target": "docs_archive_live_daemon_testing_log_parallel_tasks", "relation": "contains", "confidence": "EXTRACTED", "source_file": "D:\\AI\\Jim\\docs_archive\\LIVE_DAEMON_TESTING_LOG.md", "source_location": "L180", "weight": 1.0}, {"source": "docs_archive_live_daemon_testing_log_live_daemon_testing_log_phase_2_parallel", "target": "docs_archive_live_daemon_testing_log_daily_checklist", "relation": "contains", "confidence": "EXTRACTED", "source_file": "D:\\AI\\Jim\\docs_archive\\LIVE_DAEMON_TESTING_LOG.md", "source_location": "L196", "weight": 1.0}, {"source": "docs_archive_live_daemon_testing_log_live_daemon_testing_log_phase_2_parallel", "target": "docs_archive_live_daemon_testing_log_success_criteria_tracker", "relation": "contains", "confidence": "EXTRACTED", "source_file": "D:\\AI\\Jim\\docs_archive\\LIVE_DAEMON_TESTING_LOG.md", "source_location": "L214", "weight": 1.0}, {"source": "docs_archive_live_daemon_testing_log_live_daemon_testing_log_phase_2_parallel", "target": "docs_archive_live_daemon_testing_log_end_of_test_summary_to_complete_may_20", "relation": "contains", "confidence": "EXTRACTED", "source_file": "D:\\AI\\Jim\\docs_archive\\LIVE_DAEMON_TESTING_LOG.md", "source_location": "L226", "weight": 1.0}, {"source": "docs_archive_live_daemon_testing_log_live_daemon_testing_log_phase_2_parallel", "target": "docs_archive_live_daemon_testing_log_phase_2_completion", "relation": "contains", "confidence": "EXTRACTED", "source_file": "D:\\AI\\Jim\\docs_archive\\LIVE_DAEMON_TESTING_LOG.md", "source_location": "L242", "weight": 1.0}], "input_tokens": 0, "output_tokens": 0}